otel_tracer/__init__.py
otel_tracer/tracing/__init__.py
otel_tracer/tracing/tracer.py
otel_tracer/tracing/queue_instrumentor/__init__.py
otel_tracer/tracing/queue_instrumentor/package.py
otel_tracer/tracing/queue_instrumentor/version.py
otel_tracer/tracing/threading_instrumentor/__init__.py
otel_tracer/tracing/threading_instrumentor/package.py
otel_tracer/tracing/threading_instrumentor/version.py
otel_tracer-0.1.0.dist-info/METADATA
otel_tracer-0.1.0.dist-info/WHEEL
otel_tracer-0.1.0.dist-info/top_level.txt
otel_tracer-0.1.0.dist-info/RECORD
